MANIFEST.in
README.rst
setup.py
django_tagify/__init__.py
django_tagify/fields.py
django_tagify/settings.py
django_tagify/tests.py
django_tagify/widgets.py
django_tagify.egg-info/PKG-INFO
django_tagify.egg-info/SOURCES.txt
django_tagify.egg-info/dependency_links.txt
django_tagify.egg-info/requires.txt
django_tagify.egg-info/top_level.txt
django_tagify/static/css/tagify.css
django_tagify/static/js/jQuery.tagify.min.js
django_tagify/static/js/tagify.js
django_tagify/static/js/tagify.polyfills.js
django_tagify/templates/attrs.html
django_tagify/templates/tagsinput.html